[
    [
        {
            "nom": "La",
            "lemme": "le"
        },
        {
            "nom": "neurotechnologie",
            "lemme": "neurotechnologie"
        },
        {
            "nom": "désigne",
            "lemme": "désigner"
        },
        {
            "nom": "toute",
            "lemme": "tout"
        },
        {
            "nom": "technologie",
            "lemme": "technologie"
        },
        {
            "nom": "ayant",
            "lemme": "avoir"
        },
        {
            "nom": "une",
            "lemme": "un"
        },
        {
            "nom": "influence",
            "lemme": "influence"
        },
        {
            "nom": "fondamentale",
            "lemme": "fondamental"
        },
        {
            "nom": "sur",
            "lemme": "sur"
        },
        {
            "nom": "la",
            "lemme": "le"
        },
        {
            "nom": "manière",
            "lemme": "manière"
        },
        {
            "nom": "dont",
            "lemme": "dont"
        },
        {
            "nom": "sont",
            "lemme": "être"
        },
        {
            "nom": "compris",
            "lemme": "compris"
        },
        {
            "nom": "le",
            "lemme": "le"
        },
        {
            "nom": "cerveau",
            "lemme": "cerveau"
        },
        {
            "nom": "et",
            "lemme": "et"
        },
        {
            "nom": "ses",
            "lemme": "son"
        },
        {
            "nom": "fonctions",
            "lemme": "fonction"
        },
        {
            "nom": "supérieures",
            "lemme": "supérieur"
        },
        {
            "nom": ",",
            "lemme": ","
        },
        {
            "nom": "les",
            "lemme": "le"
        },
        {
            "nom": "différents",
            "lemme": "différent"
        },
        {
            "nom": "aspects",
            "lemme": "aspect"
        },
        {
            "nom": "de",
            "lemme": "de"
        },
        {
            "nom": "la",
            "lemme": "le"
        },
        {
            "nom": "conscience",
            "lemme": "conscience"
        },
        {
            "nom": "et",
            "lemme": "et"
        },
        {
            "nom": "de",
            "lemme": "de"
        },
        {
            "nom": "la",
            "lemme": "le"
        },
        {
            "nom": "pensée",
            "lemme": "pensée"
        },
        {
            "nom": ".",
            "lemme": "."
        }
    ],
    [
        {
            "nom": "Elle",
            "lemme": "lui"
        },
        {
            "nom": "inclut",
            "lemme": "inclure"
        },
        {
            "nom": "également",
            "lemme": "également"
        },
        {
            "nom": "les",
            "lemme": "le"
        },
        {
            "nom": "technologies",
            "lemme": "technologie"
        },
        {
            "nom": "visant",
            "lemme": "viser"
        },
        {
            "nom": "à",
            "lemme": "à"
        },
        {
            "nom": "réparer",
            "lemme": "réparer"
        },
        {
            "nom": ",",
            "lemme": ","
        },
        {
            "nom": "voire",
            "lemme": "voire"
        },
        {
            "nom": "améliorer",
            "lemme": "améliorer"
        },
        {
            "nom": "le",
            "lemme": "le"
        },
        {
            "nom": "fonctionnement",
            "lemme": "fonctionnement"
        },
        {
            "nom": "du",
            "lemme": "de"
        },
        {
            "nom": "cerveau",
            "lemme": "cerveau"
        },
        {
            "nom": "ainsi",
            "lemme": "ainsi"
        },
        {
            "nom": "que",
            "lemme": "que"
        },
        {
            "nom": "celles",
            "lemme": "celui"
        },
        {
            "nom": "qui",
            "lemme": "qui"
        },
        {
            "nom": "permettent",
            "lemme": "permettre"
        },
        {
            "nom": "aux",
            "lemme": "à"
        },
        {
            "nom": "chercheurs",
            "lemme": "chercheur"
        },
        {
            "nom": "et",
            "lemme": "et"
        },
        {
            "nom": "cliniciens",
            "lemme": "clinicien"
        },
        {
            "nom": "de",
            "lemme": "de"
        },
        {
            "nom": "visualiser",
            "lemme": "visualiser"
        },
        {
            "nom": "le",
            "lemme": "le"
        },
        {
            "nom": "cerveau",
            "lemme": "cerveau"
        },
        {
            "nom": ".",
            "lemme": "."
        }
    ],
    [
        {
            "nom": "Histoire",
            "lemme": "histoire"
        },
        {
            "nom": "Technologies",
            "lemme": "technologie"
        },
        {
            "nom": "actuelles",
            "lemme": "actuel"
        },
        {
            "nom": "Aujourd'hui",
            "lemme": "aujourd'hui"
        },
        {
            "nom": ",",
            "lemme": ","
        },
        {
            "nom": "la",
            "lemme": "le"
        },
        {
            "nom": "neurotechnologie",
            "lemme": "neurotechnologie"
        },
        {
            "nom": "est",
            "lemme": "être"
        },
        {
            "nom": "en",
            "lemme": "en"
        },
        {
            "nom": "cours",
            "lemme": "cours"
        },
        {
            "nom": "de",
            "lemme": "de"
        },
        {
            "nom": "développement",
            "lemme": "développement"
        },
        {
            "nom": ".",
            "lemme": "."
        }
    ],
    [
        {
            "nom": "Neuralink",
            "lemme": "Neuralink"
        },
        {
            "nom": "est",
            "lemme": "être"
        },
        {
            "nom": "une",
            "lemme": "un"
        },
        {
            "nom": "startup",
            "lemme": "startup"
        },
        {
            "nom": "américaine",
            "lemme": "américain"
        },
        {
            "nom": "de",
            "lemme": "de"
        },
        {
            "nom": "neurotechnologie",
            "lemme": "neurotechnologie"
        },
        {
            "nom": "qui",
            "lemme": "qui"
        },
        {
            "nom": "travaille",
            "lemme": "travailler"
        },
        {
            "nom": "actuellement",
            "lemme": "actuellement"
        },
        {
            "nom": "sur",
            "lemme": "sur"
        },
        {
            "nom": "cette",
            "lemme": "ce"
        },
        {
            "nom": "technologie",
            "lemme": "technologie"
        },
        {
            "nom": "depuis",
            "lemme": "depuis"
        },
        {
            "nom": "sa",
            "lemme": "son"
        },
        {
            "nom": "création",
            "lemme": "création"
        },
        {
            "nom": "en",
            "lemme": "en"
        },
        {
            "nom": "2016",
            "lemme": "2016"
        },
        {
            "nom": ".",
            "lemme": "."
        }
    ],
    [
        {
            "nom": "Son",
            "lemme": "son"
        },
        {
            "nom": "créateur",
            "lemme": "créateur"
        },
        {
            "nom": "est",
            "lemme": "être"
        },
        {
            "nom": "Elon",
            "lemme": "Elon"
        },
        {
            "nom": "Musk",
            "lemme": "Musk"
        },
        {
            "nom": ",",
            "lemme": ","
        },
        {
            "nom": "le",
            "lemme": "le"
        },
        {
            "nom": "célèbre",
            "lemme": "célèbre"
        },
        {
            "nom": "entrepreneur",
            "lemme": "entrepreneur"
        },
        {
            "nom": ",",
            "lemme": ","
        },
        {
            "nom": "investisseur",
            "lemme": "investisseur"
        },
        {
            "nom": "et",
            "lemme": "et"
        },
        {
            "nom": "businessman",
            "lemme": "businessman"
        },
        {
            "nom": "milliardaire",
            "lemme": "milliardaire"
        },
        {
            "nom": "de",
            "lemme": "de"
        },
        {
            "nom": "nationalité",
            "lemme": "nationalité"
        },
        {
            "nom": "(",
            "lemme": "("
        },
        {
            "nom": "sud-africano-canado-américain",
            "lemme": "sud-africano-canado-américain"
        },
        {
            "nom": ")",
            "lemme": ")"
        },
        {
            "nom": ".",
            "lemme": "."
        }
    ],
    [
        {
            "nom": "Elle",
            "lemme": "lui"
        },
        {
            "nom": "est",
            "lemme": "être"
        },
        {
            "nom": "spécialisée",
            "lemme": "spécialiser"
        },
        {
            "nom": "dans",
            "lemme": "dans"
        },
        {
            "nom": "le",
            "lemme": "le"
        },
        {
            "nom": "développement",
            "lemme": "développement"
        },
        {
            "nom": "des",
            "lemme": "de"
        },
        {
            "nom": "implants",
            "lemme": "implant"
        },
        {
            "nom": "cérébraux",
            "lemme": "cérébral"
        },
        {
            "nom": "d'",
            "lemme": "de"
        },
        {
            "nom": "interfaces",
            "lemme": "interface"
        },
        {
            "nom": "directes",
            "lemme": "direct"
        },
        {
            "nom": "neuronales",
            "lemme": "neuronal"
        },
        {
            "nom": ".",
            "lemme": "."
        }
    ],
    [
        {
            "nom": "Les",
            "lemme": "le"
        },
        {
            "nom": "travaux",
            "lemme": "travail"
        },
        {
            "nom": "sont",
            "lemme": "être"
        },
        {
            "nom": "en",
            "lemme": "en"
        },
        {
            "nom": "cours",
            "lemme": "cours"
        },
        {
            "nom": "à",
            "lemme": "à"
        },
        {
            "nom": "travers",
            "lemme": "travers"
        },
        {
            "nom": "des",
            "lemme": "de"
        },
        {
            "nom": "recherches",
            "lemme": "recherche"
        },
        {
            "nom": ",",
            "lemme": ","
        },
        {
            "nom": "des",
            "lemme": "un"
        },
        {
            "nom": "tests",
            "lemme": "test"
        },
        {
            "nom": "et",
            "lemme": "et"
        },
        {
            "nom": "des",
            "lemme": "un"
        },
        {
            "nom": "analyses",
            "lemme": "analyse"
        },
        {
            "nom": ".",
            "lemme": "."
        }
    ],
    [
        {
            "nom": "Technologies",
            "lemme": "technologie"
        },
        {
            "nom": "futures",
            "lemme": "futur"
        },
        {
            "nom": "La",
            "lemme": "le"
        },
        {
            "nom": "neurotechnologie",
            "lemme": "neurotechnologie"
        },
        {
            "nom": "est",
            "lemme": "être"
        },
        {
            "nom": "une",
            "lemme": "un"
        },
        {
            "nom": "future",
            "lemme": "future"
        },
        {
            "nom": "technologie",
            "lemme": "technologie"
        },
        {
            "nom": "scientifique",
            "lemme": "scientifique"
        },
        {
            "nom": "qui",
            "lemme": "qui"
        },
        {
            "nom": "a",
            "lemme": "avoir"
        },
        {
            "nom": "pour",
            "lemme": "pour"
        },
        {
            "nom": "but",
            "lemme": "but"
        },
        {
            "nom": "d'",
            "lemme": "de"
        },
        {
            "nom": "améliorer",
            "lemme": "améliorer"
        },
        {
            "nom": "les",
            "lemme": "le"
        },
        {
            "nom": "capacités",
            "lemme": "capacité"
        },
        {
            "nom": "futurs",
            "lemme": "futur"
        },
        {
            "nom": "des",
            "lemme": "de"
        },
        {
            "nom": "humains",
            "lemme": "humain"
        },
        {
            "nom": "à",
            "lemme": "à"
        },
        {
            "nom": "travers",
            "lemme": "travers"
        },
        {
            "nom": "plusieurs",
            "lemme": "plusieurs"
        },
        {
            "nom": "domaines",
            "lemme": "domaine"
        },
        {
            "nom": "qui",
            "lemme": "qui"
        },
        {
            "nom": "dominent",
            "lemme": "dominer"
        },
        {
            "nom": "notre",
            "lemme": "notre"
        },
        {
            "nom": "société",
            "lemme": "société"
        },
        {
            "nom": ".",
            "lemme": "."
        }
    ],
    [
        {
            "nom": "Entre",
            "lemme": "entrer"
        },
        {
            "nom": "2030",
            "lemme": "2030"
        },
        {
            "nom": "et",
            "lemme": "et"
        },
        {
            "nom": "2100",
            "lemme": "2100"
        },
        {
            "nom": ",",
            "lemme": ","
        },
        {
            "nom": "de",
            "lemme": "de"
        },
        {
            "nom": "nombreuses",
            "lemme": "nombreux"
        },
        {
            "nom": "découvertes",
            "lemme": "découverte"
        },
        {
            "nom": "et",
            "lemme": "et"
        },
        {
            "nom": "avancées",
            "lemme": "avancer"
        },
        {
            "nom": ",",
            "lemme": ","
        },
        {
            "nom": "seront",
            "lemme": "être"
        },
        {
            "nom": "positifs",
            "lemme": "positif"
        },
        {
            "nom": ",",
            "lemme": ","
        },
        {
            "nom": "à",
            "lemme": "à"
        },
        {
            "nom": "l'",
            "lemme": "le"
        },
        {
            "nom": "émergence",
            "lemme": "émergence"
        },
        {
            "nom": "de",
            "lemme": "de"
        },
        {
            "nom": "cette",
            "lemme": "ce"
        },
        {
            "nom": "nouvelle",
            "lemme": "nouveau"
        },
        {
            "nom": "technologie",
            "lemme": "technologie"
        },
        {
            "nom": ".",
            "lemme": "."
        }
    ],
    [
        {
            "nom": "Commerce",
            "lemme": "commerce"
        },
        {
            "nom": ",",
            "lemme": ","
        },
        {
            "nom": "Agriculture",
            "lemme": "agriculture"
        },
        {
            "nom": ",",
            "lemme": ","
        },
        {
            "nom": "Communication",
            "lemme": "communication"
        },
        {
            "nom": ",",
            "lemme": ","
        },
        {
            "nom": "BTP",
            "lemme": "BTP"
        },
        {
            "nom": "sont",
            "lemme": "être"
        },
        {
            "nom": "des",
            "lemme": "un"
        },
        {
            "nom": "exemples",
            "lemme": "exemple"
        },
        {
            "nom": "de",
            "lemme": "de"
        },
        {
            "nom": "domaines",
            "lemme": "domaine"
        },
        {
            "nom": "qui",
            "lemme": "qui"
        },
        {
            "nom": "ont",
            "lemme": "avoir"
        },
        {
            "nom": "un",
            "lemme": "un"
        },
        {
            "nom": "impact",
            "lemme": "impact"
        },
        {
            "nom": "énorme",
            "lemme": "énorme"
        },
        {
            "nom": "dans",
            "lemme": "dans"
        },
        {
            "nom": "notre",
            "lemme": "notre"
        },
        {
            "nom": "société",
            "lemme": "société"
        },
        {
            "nom": ".",
            "lemme": "."
        }
    ],
    [
        {
            "nom": "Les",
            "lemme": "le"
        },
        {
            "nom": "outils",
            "lemme": "outil"
        },
        {
            "nom": "de",
            "lemme": "de"
        },
        {
            "nom": "production",
            "lemme": "production"
        },
        {
            "nom": "électriques",
            "lemme": "électrique"
        },
        {
            "nom": "améliorés",
            "lemme": "améliorer"
        },
        {
            "nom": ",",
            "lemme": ","
        },
        {
            "nom": "les",
            "lemme": "le"
        },
        {
            "nom": "lunettes",
            "lemme": "lunette"
        },
        {
            "nom": "connectés",
            "lemme": "connecté"
        },
        {
            "nom": ",",
            "lemme": ","
        },
        {
            "nom": "la",
            "lemme": "le"
        },
        {
            "nom": "6",
            "lemme": "6"
        },
        {
            "nom": "G",
            "lemme": "gramme"
        },
        {
            "nom": ",",
            "lemme": ","
        },
        {
            "nom": "la",
            "lemme": "le"
        },
        {
            "nom": "généralisation",
            "lemme": "généralisation"
        },
        {
            "nom": "mondiale",
            "lemme": "mondial"
        },
        {
            "nom": "de",
            "lemme": "de"
        },
        {
            "nom": "la",
            "lemme": "le"
        },
        {
            "nom": "connexion",
            "lemme": "connexion"
        },
        {
            "nom": "satellite",
            "lemme": "satellite"
        },
        {
            "nom": ",",
            "lemme": ","
        },
        {
            "nom": "l'",
            "lemme": "le"
        },
        {
            "nom": "automatisation",
            "lemme": "automatisation"
        },
        {
            "nom": "des",
            "lemme": "de"
        },
        {
            "nom": "tâches",
            "lemme": "tâche"
        },
        {
            "nom": "à",
            "lemme": "à"
        },
        {
            "nom": "plus",
            "lemme": "plus"
        },
        {
            "nom": "grande",
            "lemme": "grand"
        },
        {
            "nom": "l'",
            "lemme": "le"
        },
        {
            "nom": "échelle",
            "lemme": "échelle"
        },
        {
            "nom": ",",
            "lemme": ","
        },
        {
            "nom": "la",
            "lemme": "le"
        },
        {
            "nom": "dématérialisation",
            "lemme": "dématérialisation"
        },
        {
            "nom": "des",
            "lemme": "de"
        },
        {
            "nom": "documents",
            "lemme": "document"
        },
        {
            "nom": "à",
            "lemme": "à"
        },
        {
            "nom": "des",
            "lemme": "un"
        },
        {
            "nom": "niveaux",
            "lemme": "niveau"
        },
        {
            "nom": "plus",
            "lemme": "plus"
        },
        {
            "nom": "grands",
            "lemme": "grand"
        },
        {
            "nom": ",",
            "lemme": ","
        },
        {
            "nom": "etc.",
            "lemme": "etc."
        },
        {
            "nom": "Ce",
            "lemme": "ce"
        },
        {
            "nom": "sont",
            "lemme": "être"
        },
        {
            "nom": "des",
            "lemme": "un"
        },
        {
            "nom": "exemples",
            "lemme": "exemple"
        },
        {
            "nom": "clairs",
            "lemme": "clair"
        },
        {
            "nom": ",",
            "lemme": ","
        },
        {
            "nom": "de",
            "lemme": "de"
        },
        {
            "nom": "nouveauté",
            "lemme": "nouveauté"
        },
        {
            "nom": "pour",
            "lemme": "pour"
        },
        {
            "nom": "notre",
            "lemme": "notre"
        },
        {
            "nom": "société",
            "lemme": "société"
        },
        {
            "nom": "de",
            "lemme": "de"
        },
        {
            "nom": "demain",
            "lemme": "demain"
        },
        {
            "nom": ".",
            "lemme": "."
        }
    ],
    [
        {
            "nom": "Les",
            "lemme": "le"
        },
        {
            "nom": "intelligences",
            "lemme": "intelligence"
        },
        {
            "nom": "artificielles",
            "lemme": "artificielle"
        },
        {
            "nom": "sont",
            "lemme": "être"
        },
        {
            "nom": "un",
            "lemme": "un"
        },
        {
            "nom": "exemple",
            "lemme": "exemple"
        },
        {
            "nom": "majeur",
            "lemme": "majeur"
        },
        {
            "nom": ",",
            "lemme": ","
        },
        {
            "nom": "car",
            "lemme": "car"
        },
        {
            "nom": "leurs",
            "lemme": "leur"
        },
        {
            "nom": "capacités",
            "lemme": "capacité"
        },
        {
            "nom": "sont",
            "lemme": "être"
        },
        {
            "nom": "considérés",
            "lemme": "considérer"
        },
        {
            "nom": "comme",
            "lemme": "comme"
        },
        {
            "nom": "super",
            "lemme": "super"
        },
        {
            "nom": "intelligentes",
            "lemme": "intelligente"
        },
        {
            "nom": ".",
            "lemme": "."
        }
    ],
    [
        {
            "nom": "L'",
            "lemme": "le"
        },
        {
            "nom": "humanité",
            "lemme": "humanité"
        },
        {
            "nom": "disposera",
            "lemme": "disposer"
        },
        {
            "nom": "de",
            "lemme": "de"
        },
        {
            "nom": "meilleurs",
            "lemme": "meilleur"
        },
        {
            "nom": "outils",
            "lemme": "outil"
        },
        {
            "nom": "technologiques",
            "lemme": "technologique"
        },
        {
            "nom": "pour",
            "lemme": "pour"
        },
        {
            "nom": "avoir",
            "lemme": "avoir"
        },
        {
            "nom": "un",
            "lemme": "un"
        },
        {
            "nom": "meilleur",
            "lemme": "meilleur"
        },
        {
            "nom": "traitement",
            "lemme": "traitement"
        },
        {
            "nom": "de",
            "lemme": "de"
        },
        {
            "nom": "l'",
            "lemme": "le"
        },
        {
            "nom": "information",
            "lemme": "information"
        },
        {
            "nom": ".",
            "lemme": "."
        }
    ],
    [
        {
            "nom": "La",
            "lemme": "le"
        },
        {
            "nom": "singularité",
            "lemme": "singularité"
        },
        {
            "nom": "technologique",
            "lemme": "technologique"
        },
        {
            "nom": "est",
            "lemme": "être"
        },
        {
            "nom": "un",
            "lemme": "un"
        },
        {
            "nom": "grand",
            "lemme": "grand"
        },
        {
            "nom": "projet",
            "lemme": "projet"
        },
        {
            "nom": "futur",
            "lemme": "futur"
        },
        {
            "nom": "de",
            "lemme": "de"
        },
        {
            "nom": "l'",
            "lemme": "le"
        },
        {
            "nom": "humanité",
            "lemme": "humanité"
        },
        {
            "nom": ",",
            "lemme": ","
        },
        {
            "nom": "qui",
            "lemme": "qui"
        },
        {
            "nom": "verrait",
            "lemme": "voir"
        },
        {
            "nom": "ses",
            "lemme": "son"
        },
        {
            "nom": "débuts",
            "lemme": "début"
        },
        {
            "nom": "avec",
            "lemme": "avec"
        },
        {
            "nom": "l'",
            "lemme": "le"
        },
        {
            "nom": "arrivée",
            "lemme": "arrivée"
        },
        {
            "nom": "en",
            "lemme": "en"
        },
        {
            "nom": "majorité",
            "lemme": "majorité"
        },
        {
            "nom": "des",
            "lemme": "de"
        },
        {
            "nom": "robots",
            "lemme": "robot"
        },
        {
            "nom": "intelligents",
            "lemme": "intelligent"
        },
        {
            "nom": ",",
            "lemme": ","
        },
        {
            "nom": "aussi",
            "lemme": "aussi"
        },
        {
            "nom": "appelés",
            "lemme": "appeler"
        },
        {
            "nom": "intelligences",
            "lemme": "intelligence"
        },
        {
            "nom": "artificielles",
            "lemme": "artificielle"
        },
        {
            "nom": "(",
            "lemme": "("
        },
        {
            "nom": "IA",
            "lemme": "ia"
        },
        {
            "nom": ")",
            "lemme": ")"
        },
        {
            "nom": ".",
            "lemme": "."
        }
    ],
    [
        {
            "nom": "Les",
            "lemme": "le"
        },
        {
            "nom": "améliorations",
            "lemme": "amélioration"
        },
        {
            "nom": "se",
            "lemme": "se"
        },
        {
            "nom": "font",
            "lemme": "faire"
        },
        {
            "nom": "de",
            "lemme": "de"
        },
        {
            "nom": "manière",
            "lemme": "manière"
        },
        {
            "nom": "permanente",
            "lemme": "permanent"
        },
        {
            "nom": ",",
            "lemme": ","
        },
        {
            "nom": "dans",
            "lemme": "dans"
        },
        {
            "nom": "l'",
            "lemme": "le"
        },
        {
            "nom": "objectif",
            "lemme": "objectif"
        },
        {
            "nom": "de",
            "lemme": "de"
        },
        {
            "nom": "moderniser",
            "lemme": "moderniser"
        },
        {
            "nom": "progressivement",
            "lemme": "progressivement"
        },
        {
            "nom": "notre",
            "lemme": "notre"
        },
        {
            "nom": "société",
            "lemme": "société"
        },
        {
            "nom": ".",
            "lemme": "."
        }
    ],
    [
        {
            "nom": "Le",
            "lemme": "le"
        },
        {
            "nom": "projet",
            "lemme": "projet"
        },
        {
            "nom": "se",
            "lemme": "se"
        },
        {
            "nom": "déroulera",
            "lemme": "dérouler"
        },
        {
            "nom": "au",
            "lemme": "au"
        },
        {
            "nom": "fur",
            "lemme": "fur"
        },
        {
            "nom": "et",
            "lemme": "et"
        },
        {
            "nom": "à",
            "lemme": "à"
        },
        {
            "nom": "mesure",
            "lemme": "mesure"
        },
        {
            "nom": ",",
            "lemme": ","
        },
        {
            "nom": "il",
            "lemme": "il"
        },
        {
            "nom": "subira",
            "lemme": "subir"
        },
        {
            "nom": "des",
            "lemme": "de"
        },
        {
            "nom": "changements",
            "lemme": "changement"
        },
        {
            "nom": "massifs",
            "lemme": "massif"
        },
        {
            "nom": ",",
            "lemme": ","
        },
        {
            "nom": "tout",
            "lemme": "tout"
        },
        {
            "nom": "au",
            "lemme": "au"
        },
        {
            "nom": "long",
            "lemme": "long"
        },
        {
            "nom": "du",
            "lemme": "de"
        },
        {
            "nom": "XXIème",
            "lemme": "xxième"
        },
        {
            "nom": "siècle",
            "lemme": "siècle"
        },
        {
            "nom": ".",
            "lemme": "."
        }
    ],
    [
        {
            "nom": "Tout",
            "lemme": "tout"
        },
        {
            "nom": "ce",
            "lemme": "ce"
        },
        {
            "nom": "processus",
            "lemme": "processus"
        },
        {
            "nom": ",",
            "lemme": ","
        },
        {
            "nom": "se",
            "lemme": "se"
        },
        {
            "nom": "fera",
            "lemme": "faire"
        },
        {
            "nom": "pendant",
            "lemme": "pendant"
        },
        {
            "nom": "des",
            "lemme": "un"
        },
        {
            "nom": "décennies",
            "lemme": "décennie"
        },
        {
            "nom": "à",
            "lemme": "à"
        },
        {
            "nom": "partir",
            "lemme": "partir"
        },
        {
            "nom": "des",
            "lemme": "un"
        },
        {
            "nom": "années",
            "lemme": "année"
        },
        {
            "nom": "2040",
            "lemme": "2040"
        },
        {
            "nom": ".",
            "lemme": "."
        }
    ],
    [
        {
            "nom": "Éthique",
            "lemme": "éthique"
        },
        {
            "nom": "Notes",
            "lemme": "note"
        },
        {
            "nom": "et",
            "lemme": "et"
        },
        {
            "nom": "références",
            "lemme": "référence"
        },
        {
            "nom": "Annexes",
            "lemme": "annexe"
        },
        {
            "nom": "Articles",
            "lemme": "article"
        },
        {
            "nom": "connexes",
            "lemme": "connexe"
        },
        {
            "nom": "Neuroscience",
            "lemme": "neuroscience"
        },
        {
            "nom": "Neuro-ingénierie",
            "lemme": "neuro-ingénierie"
        },
        {
            "nom": "Cerveau",
            "lemme": "Cerveau"
        },
        {
            "nom": "artificiel",
            "lemme": "artificiel"
        },
        {
            "nom": "Liberté",
            "lemme": "Liberté"
        },
        {
            "nom": "cognitive",
            "lemme": "cognitif"
        },
        {
            "nom": "Liens",
            "lemme": "lien"
        },
        {
            "nom": "externes",
            "lemme": "externe"
        },
        {
            "nom": "Qu'",
            "lemme": "que"
        },
        {
            "nom": "est",
            "lemme": "être"
        },
        {
            "nom": "-ce",
            "lemme": "-ce"
        },
        {
            "nom": "que",
            "lemme": "que"
        },
        {
            "nom": "l'",
            "lemme": "le"
        },
        {
            "nom": "intelligence",
            "lemme": "intelligence"
        },
        {
            "nom": "artificielle",
            "lemme": "artificiel"
        },
        {
            "nom": "(",
            "lemme": "("
        },
        {
            "nom": "IA",
            "lemme": "ia"
        },
        {
            "nom": ")",
            "lemme": ")"
        },
        {
            "nom": "?",
            "lemme": "?"
        }
    ],
    [
        {
            "nom": ",",
            "lemme": ","
        },
        {
            "nom": "sur",
            "lemme": "sur"
        },
        {
            "nom": "ibm.com",
            "lemme": "ibm.com"
        },
        {
            "nom": "(",
            "lemme": "("
        },
        {
            "nom": "consulté",
            "lemme": "consulter"
        },
        {
            "nom": "le",
            "lemme": "le"
        },
        {
            "nom": "17",
            "lemme": "17"
        },
        {
            "nom": "novembre",
            "lemme": "novembre"
        },
        {
            "nom": "2023",
            "lemme": "2023"
        },
        {
            "nom": ")",
            "lemme": ")"
        },
        {
            "nom": "https://www.futurebusinesstech.com/",
            "lemme": "https://www.futurebusinesstech.com/"
        },
        {
            "nom": "Portail",
            "lemme": "Portail"
        },
        {
            "nom": "de",
            "lemme": "de"
        },
        {
            "nom": "la",
            "lemme": "le"
        },
        {
            "nom": "médecine",
            "lemme": "médecine"
        },
        {
            "nom": "Portail",
            "lemme": "Portail"
        },
        {
            "nom": "des",
            "lemme": "de"
        },
        {
            "nom": "neurosciences",
            "lemme": "neuroscience"
        },
        {
            "nom": "Portail",
            "lemme": "Portail"
        },
        {
            "nom": "des",
            "lemme": "de"
        },
        {
            "nom": "technologies",
            "lemme": "technologie"
        }
    ]
]